zxtx/__init__.py
zxtx/__main__.py
zxtx/cli.py
zxtx/constants.py
zxtx/decryption.py
zxtx/dtypes.py
zxtx/encryption.py
zxtx/highlevel.py
zxtx/parser.py
zxtx/signer.py
zxtx/utils.py
zxtx/verifier.py
zxtx/writer.py
zxtx-0.1.3.dist-info/licenses/LICENSE
zxtx-0.1.3.dist-info/METADATA
zxtx-0.1.3.dist-info/WHEEL
zxtx-0.1.3.dist-info/entry_points.txt
zxtx-0.1.3.dist-info/top_level.txt
zxtx-0.1.3.dist-info/RECORD
