Metadata-Version: 2.4
Name: zxtx
Version: 0.1.3
Summary: ZXTX file format support.
Home-page: https://github.com/voyager-2021/zxtx
Author: voyager-2021
Author-email: voyager-2019@outlook.com
License: MIT
Project-URL: Documentation, https://github.com/voyager-2021/zxtx#readme
Project-URL: Source, https://github.com/voyager-2021/zxtx
Project-URL: Issues, https://github.com/voyager-2021/zxtx/issues
Keywords: compression,encryption,file-format,zxtx,cryptography
Classifier: Development Status :: 3 - Alpha
Classifier: Intended Audience :: Developers
Classifier: Programming Language :: Python :: 3
Classifier: Programming Language :: Python :: 3.10
Classifier: Programming Language :: Python :: 3.11
Classifier: Programming Language :: Python :: 3.12
Classifier: Programming Language :: Python :: 3.13
Classifier: Topic :: Security :: Cryptography
Classifier: Topic :: File Formats
Requires-Python: >=3.10
License-File: LICENSE
Requires-Dist: cryptography>=45.0.1
Requires-Dist: brotli>=1.1.0
Provides-Extra: dev
Requires-Dist: pytest>=8.3.5; extra == "dev"
Requires-Dist: black>=25.1.0; extra == "dev"
Requires-Dist: mypy>=1.15.0; extra == "dev"
Requires-Dist: isort>=6.0.1; extra == "dev"
Requires-Dist: pydocstyle>=6.3.0; extra == "dev"
Requires-Dist: pylint>=3.3.7; extra == "dev"
Requires-Dist: bandit>=1.8.3; extra == "dev"
Requires-Dist: safety>=3.5.1; extra == "dev"
Requires-Dist: flake8>=7.2.0; extra == "dev"
Requires-Dist: tox>=4.26.0; extra == "dev"
Requires-Dist: coverage>=7.8.1; extra == "dev"
Requires-Dist: pytest-cov>=6.1.1; extra == "dev"
Requires-Dist: pre-commit>=4.2.0; extra == "dev"
Requires-Dist: twine>=6.0.1; extra == "dev"
Requires-Dist: build>=1.2.2.post1; extra == "dev"
Provides-Extra: opt
Requires-Dist: rich>=14.0.0; extra == "opt"
Provides-Extra: docs
Requires-Dist: sphinx>=8.2.3; extra == "docs"
Requires-Dist: sphinx-rtd-theme>=3.0.2; extra == "docs"
Requires-Dist: sphinx-autobuild>=2024.10.3; extra == "docs"
Dynamic: license-file
